{
  "[Animated Manga] Shiraken Scholar Society - Ex. 5: Chocolate! #しらけん": "EgslhA4_GlQ",
  "綺麗事 / 星街すいせい(official)": "VPhLXeU25KA",
  "もうどうなってもいいや / 星街すいせい(official)": "ojZaWERcbaI",
  "Overdose / 星街すいせい×戌亥とこ(Cover)": "FVBQM1Y7ukg",
  "Caramel Pain / 星街すいせい(official)": "UpEPkPg8YP4",
  "Orbital Period / 星街すいせい(official)": "jMSXPPSmsVo",
  "ビーナスバグ / 星街すいせい(official)": "JXvOlJOGU5Y",
  "星街すいせい 3rd Album『新星目録』クロスフェード": "fqb2j_RFTP0",
  "tuki.ちゃんと星街すいせいでカラオケ行ってみた‼🌙✨（前編）": "FHgeeY_UPiI",
  "星街すいせいを解き明かせ！MV / Stellar Stellar【#AndroidかこってMUSIC】": "ZM7gdMkOgtw",
  "【YTFF2024】星街すいせい「ビビデバ」special stage": "4mdQUsD-6Y8",
  "ビヨンド 〜越えてゆこう〜 / 星街すいせい【『モアナと伝説の海２』 Special Tribute】": "IJBc-lFRpXM",
  "#星街すいせい 3rdフルアルバム『新星目録』＆Hoshimachi Suisei 日本武道館 Live “SuperNova” Teaser movie": "EYhknpRVqUs",
  "AWAKE / 星街すいせい(official)": "UYEZL13MUFk",
  "#HoshimaticProject NEW SINGLE Making Movie": "Vse0W0KlX2U",
  "W●RK / 星街すいせい×葛葉(Cover)": "lGQDHKzLznE",
  "ムーンライト / 星街すいせい(official)": "UmN7Fr_Kf-8",
  "8.32 / Startend (Cover)": "pEIo7LHOxK8",
  "シャンティ(SHANTI) / 星街すいせい(Cover)": "zNb-UneSO5c",
  "【#miComet】ドッキリ企画 未公開シーン集": "LAR-XD-w8Dg",
  "シュガーラッシュ / miComet(official)": "gtgME6MJpk4",
  "Hoshimachi Suisei - BIBBIDIBA (official)": "8ZP5eqm4JqM",
  "アンノウン・マザーグース / Hoshimatic Project(Cover)": "8bkICbOt1ck",
  "【 ロケVTR/前編 】#miComet ビジネス出張!? in シンガポール🌸☄": "aQRnywoAXes",
  "きゅうくらりん / 星街すいせい(Cover)": "QkdDWaBtK04",
  "青のすみか / 星街すいせい(Cover)": "29CDyIhI5Pc",
  "星街すいせい「Stellar Stellar - From THE FIRST TAKE」 | YTFF Japan 2023": "laJZxtGfDOw",
  "ザイオン / 星街すいせい(official)": "liCsjACEeJA",
  "[Animated Manga] Shiraken Scholar Society - Ch. 10: Performance! #しらけん": "UOz-9uTo1Lo",
  "ソワレ / 星街すいせい(official)": "mRgslQ5Z-kU",
  "星街すいせい - Shout in Crisis ダイジェスト映像": "MgJK8pSytTA",
  "THE MUSIC DAY 2023 「Stellar Stellar」ライブ映像": "nVHy8OdrYAE",
  "生き様 / 星街すいせい(Cover)": "z2TBTXYiwvo",
  "マーシャル・マキシマイザー / 星街すいせい(Cover)": "j2J0_dcHLwo",
  "【holo*27 MV】星街すいせい - プラネタリウム【ホロライブ x DECO*27】": "hAI-qjw6J-A",
  "【メンバー限定🍀】ライブ終了後に撮った動画": "UaNIRC9Y-c0",
  "みちづれ / 星街すいせい(official)": "4uqONJT6G-M",
  "[Animated Manga] Shiraken Scholar Society - Ch. 4: Trial Member! #しらけん": "qLTC9mkcSpw",
  "Shout in Crisis『みちづれ』ライブ映像": "YKTYbI5wXxw",
  "星街すいせい 『みちづれ』 メイキングムービー": "Dx0wK2MbD_c",
  "星街すいせい 2nd Album『SPECTER』クロスフェード": "xdxROihdIEY",
  "放送室 / 星街すいせい(official)": "BP59Bm6T3_I",
  "Hoshimachi Suisei 2nd Solo Live \"Shout in Crisis\" Teaser movie": "GxoD4P54AF0",
  "星街すいせい 2nd Album『Specter』ティザーPV": "lU7ZfAXFwbU",
  "灼熱にて純情(wii-wii-woo) / 星街すいせい(official)": "r1ZVPTCOCSQ",
  "星街すいせい - STELLAR into the GALAXYダイジェスト映像": "ri19Mh6Kz2I",
  "RUST season2 初めてロケット打ってみた🚀【ホロライブ / 星街すいせい】": "WtU129ZrSAA",
  "トリコロージュ / 星街すいせい(cover)": "Rc_-keez4xs",
  "幽霊東京 / 星街すいせい(cover)": "tuZty35Fk7M",
  "TEMPLATE / 星街すいせい(official)": "mBuHQeL-OO8",
  "僕は初音ミクとキスをした / 星街すいせい(cover)": "o9r6lFYK9SE",
  "ロウワー / 星街すいせい(cover)": "1KUZHKI-BDk",
  "アニマル / miComet(cover)": "9yBLZKFKXyg",
  "バイバイレイニー / 星街すいせい(official)": "3DrYQMK4hJE",
  "シネマ / 星街すいせい×奏手イヅル×アステル･レダ(Cover)": "UXQDUhSr8nU",
  "フォニイ / 星街すいせい(Cover)": "N029UUlH1Dc",
  "Stellar Stellar / 星街すいせい(official)": "a51VH9BYzZA",
  "星街すいせい 1st Album『Still Still Stellar』クロスフェード": "CrbUyoaosYE",
  "ぜんぶあんたのせい / 星街すいせい(Cover)": "XfzkyqTPafo",
  "Crazy:B「Honeycomb Summer」 / 戌亥とこ × 星街すいせい(Cover)": "aWv2KjaFqBA",
  "Hoshimachi Suisei 1st Solo Live \"STELLAR into the GALAXY\" Supported By Bushiroad Teaser movie": "P6ei0hL0sbI",
  "【DanceMV】自分勝手Dazzling / 星街すいせい(official)": "Mm87JgTx2Ao",
  "【CHUNITHM】自分勝手Dazzling / 星街すいせい(official)": "JiNIHQ28pGc",
  "Cry Baby / 星街すいせい(Cover)": "7wbd6ffvXm8",
  "駆けろ / 星街すいせい(official)": "IqT6cHCT1TE",
  "少女レイ / 星街すいせい(Cover)": "z9tsfkdgByA",
  "Bluerose / 星街すいせい(official)": "ZfDYRy17CBY",
  "GETCHA! / calliope × suisei(cover)": "EjlMPu5sEgw",
  "KING / 星街すいせい(Cover)": "mLwtfg57kbs",
  "GHOST / 星街すいせい(official)": "IKKar5SS29E",
  "Goose house「光るなら」 / 星街すいせい × 蒔田陽丸 × 楓山蓮太郎(Cover)": "68iRzgy6c00",
  "『e-ma e-ma』歌って踊ってみた【ホロライブ / 星街すいせい】": "HZmPB0f3cbI",
  "Ra*bits「メルティ♡キッチン」 / 戌亥とこ × 星街すいせい(Cover)": "KiUvL-rp1zg",
  "シド「乱舞のメロディ」 / 星街すいせい(Cover)": "LpkWFnRPd-M",
  "バックステージ映像ダイジェスト【#星街すいせい50万人記念ライブ】": "GczSWwXLr9o",
  "Valkyrie「今宵月の館にて」 / 戌亥とこ × 星街すいせい(Cover)": "vhmFj1owmuk",
  "Saint Snow「Believe Again」/ 星街すいせい×夏色まつり(Live-edition)": "JoDcaZASa8M",
  "LiSA『紅蓮華』 / 星街すいせい(Live-edition)": "Ehm_A0pYQEM",
  "D/Zeal「餞の鳥」 / ときのそら × 星街すいせい(Cover)": "5yDNEmcKQFY",
  "シャンパーニュ・デイ / 星街すいせい(cover)": "HkMXq08WlJo",
  "[Zombie Land Saga] Franchouchou \"Saga Jihen\" / Hoshimachi Suisei with Hololive Fantasy": "-wNSFmqhQsU",
  "NEXT COLOR PLANET / 星街すいせい(official)": "vQHVGXdcqEQ",
  "【あんスタ】2018年ガチャチャレまとめ【ホロライブ / 星街すいせい】": "hkeIWsK3bKM",
  "Guilty kiss「コワレヤスキ」/ 出雲霞×星街すいせい×堰代ミコ【歌ってみた】": "_PpTrPbRg0U",
  "【プロメア】superfly「覚醒」/ 星街すいせい(Cover)": "dPTeBvVJ_xY",
  "天球、彗星は夜を跨いで / 星街すいせい(official)": "zLak0dxBKpM",
  "【重大発表】待望の…〇〇〇": "XkGyqzEF7II",
  "【歌ってみた】Shine!!/CINDERELLA PROJECT【#20】": "WLj0Rg_bcvQ",
  "【歌ってみた】劣等上等【ルピナス&すいせい】": "X1T9M4F8sKk",
  "【歌ってみた】melty world【#18】": "9pgap38Os_k",
  "comet/Hoshimati Suisei": "3cqV5BKJHyk",
  "【歌ってみた】創聖のアクエリオン【#17】": "_8eUrkYNnLY",
  "【歌ってみた】ブルーバード【#15】": "PerzMoTou-k",
  "【歌ってみた】メルティランドナイトメア【#07】": "sm4KMKurd8E",
}
